TTC/__init__.py
TTC/cli.py
TTC/client.py
TTC/config.py
TTC/metrics.py
TTC/runner_base.py
TTC/runner_textgen_openai.py
TTC/storage.py
TTC/utils_nvml.py
ttcbench-0.1.5.dist-info/licenses/LICENCE
ttcbench-0.1.5.dist-info/METADATA
ttcbench-0.1.5.dist-info/WHEEL
ttcbench-0.1.5.dist-info/entry_points.txt
ttcbench-0.1.5.dist-info/top_level.txt
ttcbench-0.1.5.dist-info/RECORD
