Metadata-Version: 2.4
Name: ttcbench
Version: 0.1.5
Summary: Simple vLLM/OpenAI textgen benchmark with optional GPU telemetry from TTC library
Author-email: Bekbolat <bekbolat_omarov@list.ru>
License-Expression: MIT
Keywords: vllm,benchmark,openai,chat-completions,gpu,nvml
Classifier: Programming Language :: Python :: 3
Classifier: Operating System :: OS Independent
Requires-Python: >=3.10
License-File: LICENCE
Requires-Dist: requests>=2.32
Requires-Dist: pydantic>=2.8
Requires-Dist: python-dotenv>=1.0
Requires-Dist: nvidia-ml-py>=12.555.43
Requires-Dist: psutil>=6.0
Requires-Dist: rich>=13.7
Provides-Extra: server
Requires-Dist: fastapi>=0.111; extra == "server"
Requires-Dist: uvicorn[standard]>=0.30; extra == "server"
Dynamic: license-file
